{"0": {"SENTENCE": "She'd take the world off my shoulders\nIf it was ever hard to move.", "KEYWORDS": ["hard to move", "move", "world", "shoulders", "hard"], "TTS": {"file_name": "speech_0", "audio_file_path": "audio\\speech_0.mp3", "audio_length": 4.16}, "CAPTION_path": "caption_assets\\bfae2497-c8d6-411b-b8f9-19c6d3452658.svg", "MEDIA_ASSET": {"duration": 7, "size": "3840X3840", "link": "https://player.vimeo.com/external/468468369.hd.mp4?s=d4de5ea0a0f5eb92a9adf3737f19cef635f0a62a&profile_id=172&oauth2_token_id=57447761", "file_path": "media_assets\\e3c4dd36-523a-464f-beaf-b9a9a8ba1b3d.mp4", "keyword": "hard to move"}}, "1": {"SENTENCE": "She'd turn the rain to a rainbow\nWhen I was living in the blue.", "KEYWORDS": ["turn the rain", "blue", "turn", "rain", "rainbow"], "TTS": {"file_name": "speech_1", "audio_file_path": "audio\\speech_1.mp3", "audio_length": 3.7}, "CAPTION_path": "caption_assets\\a9ccd7e7-aee3-4db4-a8d3-5a832e0f998d.svg", "MEDIA_ASSET": {"duration": 24, "size": "1920X1920", "link": "https://player.vimeo.com/external/378993860.hd.mp4?s=3b5e45e5bd7ccb2be140f3c939f44a3738e70324&profile_id=169&oauth2_token_id=57447761", "file_path": "media_assets\\1f1a3e13-81e6-4aed-b73d-c97a2e2c83e4.mp4", "keyword": "turn the rain"}}, "2": {"SENTENCE": "Why then, if she is so perfect\nDo I still wish that it was you?.", "KEYWORDS": ["perfect"], "TTS": {"file_name": "speech_2", "audio_file_path": "audio\\speech_2.mp3", "audio_length": 4.42}, "CAPTION_path": "caption_assets\\be15211f-a184-4a89-87f8-3b039e87b689.svg", "MEDIA_ASSET": {"duration": 9, "size": "3840X3840", "link": "https://player.vimeo.com/external/436161878.hd.mp4?s=649140317f8b3448cc608fc63dd6d93758ff0947&profile_id=172&oauth2_token_id=57447761", "file_path": "media_assets\\56b2e809-0c24-4e0c-b2af-340cc3c355cc.mp4", "keyword": "perfect"}}, "3": {"SENTENCE": "Perfect don't mean that it's working\nSo what can I do? (Ooh).", "KEYWORDS": ["Ooh", "Perfect", "working"], "TTS": {"file_name": "speech_3", "audio_file_path": "audio\\speech_3.mp3", "audio_length": 4.39}, "CAPTION_path": "caption_assets\\a376a3c7-7e0c-4c2d-9ba7-128187df81ac.svg", "MEDIA_ASSET": {"link": "https://images.pexels.com/photos/327533/pexels-photo-327533.jpeg?auto=compress&cs=tinysrgb&fit=crop&h=627&w=1200", "file_path": "media_assets\\9c05b263-5073-4bec-90a3-e90b33571329.jpeg", "keyword": "Perfect"}}, "4": {"SENTENCE": "When you're out of sight\nIn my mind.", "KEYWORDS": ["mind", "sight"], "TTS": {"file_name": "speech_4", "audio_file_path": "audio\\speech_4.mp3", "audio_length": 2.81}, "CAPTION_path": "caption_assets\\216d2625-362d-4ae1-bd7d-c2af59291948.svg", "MEDIA_ASSET": {"duration": 9, "size": "1920X1920", "link": "https://player.vimeo.com/external/416321333.hd.mp4?s=39c9fbeaa796a272216d0eeb05f078ec72701e08&profile_id=175&oauth2_token_id=57447761", "file_path": "media_assets\\0947af06-635c-48a7-965c-828221fa9f45.mp4", "keyword": "mind"}}, "5": {"SENTENCE": "'Cause sometimes I look in her eyes\nAnd that's where I find a glimpse of us.", "KEYWORDS": ["find a glimpse", "eyes", "find", "glimpse"], "TTS": {"file_name": "speech_5", "audio_file_path": "audio\\speech_5.mp3", "audio_length": 4.29}, "CAPTION_path": "caption_assets\\782da6cf-5fe2-48a3-a7d4-fc59021212c6.svg", "MEDIA_ASSET": {"duration": 13, "size": "3840X3840", "link": "https://player.vimeo.com/external/389772672.hd.mp4?s=0355a01f1077f52f8979556a2815f1724bcde257&profile_id=172&oauth2_token_id=57447761", "file_path": "media_assets\\6a69f6f7-5055-47f1-9ece-458dd6e165d7.mp4", "keyword": "find a glimpse"}}, "6": {"SENTENCE": "And I try to fall for her touch\nBut I'm thinking of the way it was.", "KEYWORDS": ["fall", "touch", "thinking"], "TTS": {"file_name": "speech_6", "audio_file_path": "audio\\speech_6.mp3", "audio_length": 4.12}, "CAPTION_path": "caption_assets\\8f07fd56-77e7-4b09-bc74-de82cce9f0fa.svg", "MEDIA_ASSET": {"duration": 30, "size": "2704X2704", "link": "https://player.vimeo.com/external/469912268.hd.mp4?s=4e8213223188edefc0c9e69cc0fc0037a86d6eed&profile_id=171&oauth2_token_id=57447761", "file_path": "media_assets\\dd1a8a50-7129-45d1-9952-b877a9bb368e.mp4", "keyword": "fall"}}, "7": {"SENTENCE": "Said I'm fine and said I moved on\nI'm only here passing time in her arms.", "KEYWORDS": ["passing time", "arms", "fine", "moved", "passing"], "TTS": {"file_name": "speech_7", "audio_file_path": "audio\\speech_7.mp3", "audio_length": 4.6}, "CAPTION_path": "caption_assets\\5a66657e-2144-4239-bbcf-09aef178700d.svg", "MEDIA_ASSET": {"duration": 18, "size": "4096X4096", "link": "https://player.vimeo.com/external/401018241.hd.mp4?s=01539c07f55a7f73f783b358917f229bf2feb4a4&profile_id=173&oauth2_token_id=57447761", "file_path": "media_assets\\6d431392-5fd4-4863-ad7d-fc4c9e68cf63.mp4", "keyword": "passing time"}}, "8": {"SENTENCE": "Hoping I'll find\nA glimpse of us\nTell me he savors your glory.", "KEYWORDS": ["Hoping I find", "savors your glory", "find A glimpse", "Hoping", "glory"], "TTS": {"file_name": "speech_8", "audio_file_path": "audio\\speech_8.mp3", "audio_length": 4.76}, "CAPTION_path": "caption_assets\\aecab0b6-8f8a-421a-a71b-26fc2cdc8ef7.svg", "MEDIA_ASSET": {"duration": 13, "size": "3840X3840", "link": "https://player.vimeo.com/external/389772672.hd.mp4?s=0355a01f1077f52f8979556a2815f1724bcde257&profile_id=172&oauth2_token_id=57447761", "file_path": "media_assets\\3302d87b-2f68-406c-ae7f-9e458af9bdb9.mp4", "keyword": "Hoping I find"}}, "9": {"SENTENCE": "Does he laugh the way I did?\nIs this a part of your story?\nOne that I had never lived.", "KEYWORDS": ["laugh", "story", "lived", "part"], "TTS": {"file_name": "speech_9", "audio_file_path": "audio\\speech_9.mp3", "audio_length": 5.45}, "CAPTION_path": "caption_assets\\6a7236c7-6b5e-4095-86b4-2e451e6dbc74.svg", "MEDIA_ASSET": {"duration": 13, "size": "3840X3840", "link": "https://player.vimeo.com/external/426725959.hd.mp4?s=4f9ef092f4cbecca807c22cc889d07e84287f496&profile_id=172&oauth2_token_id=57447761", "file_path": "media_assets\\5896b882-32dd-4495-94b4-bea55b28760b.mp4", "keyword": "laugh"}}, "10": {"SENTENCE": "Maybe one day you'll feel lonely\nAnd in his eyes, you'll get a glimpse.", "KEYWORDS": ["day you feel", "feel lonely", "eyes", "glimpse", "day"], "TTS": {"file_name": "speech_10", "audio_file_path": "audio\\speech_10.mp3", "audio_length": 4.49}, "CAPTION_path": "caption_assets\\2f83a959-6769-45fd-b2e1-e0fc21cd0305.svg", "MEDIA_ASSET": {"duration": 60, "size": "3840X3840", "link": "https://player.vimeo.com/external/308153460.hd.mp4?s=bb1572aa5b9a3dbc84d27e38bc2b46b4403a7505&profile_id=172&oauth2_token_id=57447761", "file_path": "media_assets\\a9992e1a-edbd-4eee-bcf8-0009b45f4b65.mp4", "keyword": "day you feel"}}, "11": {"SENTENCE": "Maybe you'll start slipping slowly\nAnd find me again\nWhen you're out of sight.", "KEYWORDS": ["start slipping slowly", "start slipping", "slipping slowly", "slowly And find", "sight"], "TTS": {"file_name": "speech_11", "audio_file_path": "audio\\speech_11.mp3", "audio_length": 5.21}, "CAPTION_path": "caption_assets\\9e615c07-0861-448b-ae04-8b130a9f90d4.svg", "MEDIA_ASSET": {"duration": 43, "size": "1920X1920", "link": "https://player.vimeo.com/external/448842262.hd.mp4?s=8425608f3195ceb51f33eaf412701351ddd1dbb9&profile_id=175&oauth2_token_id=57447761", "file_path": "media_assets\\8df1e38e-6f52-4a51-bcb4-31f1496c2001.mp4", "keyword": "start slipping slowly"}}, "12": {"SENTENCE": "In my mind\n'Cause sometimes I look in her eyes.", "KEYWORDS": ["mind", "eyes"], "TTS": {"file_name": "speech_12", "audio_file_path": "audio\\speech_12.mp3", "audio_length": 3.4}, "CAPTION_path": "caption_assets\\ff8d3f16-2a29-446f-a6fa-737b86c985b0.svg", "MEDIA_ASSET": {"duration": 9, "size": "1920X1920", "link": "https://player.vimeo.com/external/416321333.hd.mp4?s=39c9fbeaa796a272216d0eeb05f078ec72701e08&profile_id=175&oauth2_token_id=57447761", "file_path": "media_assets\\fb826588-36ca-481b-b3e6-f57a11d94d54.mp4", "keyword": "mind"}}, "13": {"SENTENCE": "And that's where I find a glimpse of us\nAnd I try to fall for her touch\nBut I'm thinking of the way it was.", "KEYWORDS": ["find a glimpse", "find", "glimpse", "fall", "touch"], "TTS": {"file_name": "speech_13", "audio_file_path": "audio\\speech_13.mp3", "audio_length": 6.28}, "CAPTION_path": "caption_assets\\410896b7-9f83-46fa-8ea9-962910fa3662.svg", "MEDIA_ASSET": {"duration": 13, "size": "3840X3840", "link": "https://player.vimeo.com/external/389772672.hd.mp4?s=0355a01f1077f52f8979556a2815f1724bcde257&profile_id=172&oauth2_token_id=57447761", "file_path": "media_assets\\fa374567-c9a1-4d51-be48-52b491877ce1.mp4", "keyword": "find a glimpse"}}, "14": {"SENTENCE": "Said I'm fine and said I moved on\nI'm only here passing time in her arms\nHoping I'll find.", "KEYWORDS": ["Hoping I find", "arms Hoping", "passing time", "Hoping", "find"], "TTS": {"file_name": "speech_14", "audio_file_path": "audio\\speech_14.mp3", "audio_length": 6.08}, "CAPTION_path": "caption_assets\\1a88c70d-0efe-42dc-80e8-fc479bdfceb0.svg", "MEDIA_ASSET": {"duration": 13, "size": "3840X3840", "link": "https://player.vimeo.com/external/389772672.hd.mp4?s=0355a01f1077f52f8979556a2815f1724bcde257&profile_id=172&oauth2_token_id=57447761", "file_path": "media_assets\\25962856-39a4-4a50-b7b9-b75b129e85c6.mp4", "keyword": "Hoping I find"}}, "15": {"SENTENCE": "A glimpse of us\nOoh, ooh-ooh\nOoh, ooh-ooh\nOoh, ooh, ooh\n'Cause sometimes I look in her eyes\nAnd that's where I find a glimpse of us.", "KEYWORDS": ["ooh-ooh Ooh", "Ooh", "find a glimpse", "ooh-ooh", "glimpse"], "TTS": {"file_name": "speech_15", "audio_file_path": "audio\\speech_15.mp3", "audio_length": 10.34}, "CAPTION_path": "caption_assets\\823551cf-d531-402f-98cc-7b0fb379df9b.svg", "MEDIA_ASSET": {"link": "https://images.pexels.com/photos/316681/pexels-photo-316681.jpeg?auto=compress&cs=tinysrgb&fit=crop&h=627&w=1200", "file_path": "media_assets\\2d97e65a-e2b7-4393-8230-dc6d6fd482a5.jpeg", "keyword": "find a glimpse"}}, "16": {"SENTENCE": "And I try to fall for her touch\nBut I'm thinking of the way it was\nSaid I'm fine and said I moved on.", "KEYWORDS": ["fall", "touch", "thinking", "fine", "moved"], "TTS": {"file_name": "speech_16", "audio_file_path": "audio\\speech_16.mp3", "audio_length": 6.3}, "CAPTION_path": "caption_assets\\891a683b-9135-4943-b1ee-0ddfbc672c64.svg", "MEDIA_ASSET": {"duration": 30, "size": "2704X2704", "link": "https://player.vimeo.com/external/469912268.hd.mp4?s=4e8213223188edefc0c9e69cc0fc0037a86d6eed&profile_id=171&oauth2_token_id=57447761", "file_path": "media_assets\\5cc11a3c-aae3-4d47-a103-6f7dee94d494.mp4", "keyword": "fall"}}, "17": {"SENTENCE": "I'm only here passing time in her arms\nHoping I'll find\nA glimpse of us.", "KEYWORDS": ["arms Hoping", "Hoping I find", "passing time", "find A glimpse", "Hoping"], "TTS": {"file_name": "speech_17", "audio_file_path": "audio\\speech_17.mp3", "audio_length": 5.22}, "CAPTION_path": "caption_assets\\b4421854-c741-4e2c-978f-47ee66bec536.svg", "MEDIA_ASSET": {"duration": 53, "size": "4096X4096", "link": "https://player.vimeo.com/external/482563931.hd.mp4?s=8b4debf4ca7ed76aae57e82a905dd61761678eb6&profile_id=172&oauth2_token_id=57447761", "file_path": "media_assets\\7d4afcf4-10f0-4c4a-985d-b4471ef14f1a.mp4", "keyword": "arms Hoping"}}}